github_activity_visualiser/visualiser.py
github_activity_visualiser-0.1.1.dist-info/entry_points.txt
github_activity_visualiser-0.1.1.dist-info/LICENSE.txt
github_activity_visualiser-0.1.1.dist-info/WHEEL
github_activity_visualiser-0.1.1.dist-info/METADATA
github_activity_visualiser-0.1.1.dist-info/RECORD
