Metadata-Version: 2.1
Name: github-activity-visualiser
Version: 0.1.1
Summary: 
Home-page: https://github.com/esemi/github-activity-visualiser
License: MIT
Author: Simon
Author-email: spam@esemi.ru
Requires-Python: >=3.9,<4.0
Classifier: License :: OSI Approved :: MIT License
Classifier: Programming Language :: Python :: 3
Classifier: Programming Language :: Python :: 3.9
Requires-Dist: PyGithub (>=1.55,<2.0)
Requires-Dist: click (>=8.0.1,<9.0.0)
Project-URL: Repository, https://github.com/esemi/github-activity-visualiser
